{
  "openapi": "3.0.0",
  "info": {
    "title": "Form Url Encoded",
    "version": "1.0.0"
  },
  "servers": [
    {
      "url": "https://api.io"
    }
  ],
  "paths": {
    "/register": {
      "post": {
        "tags": ["default"],
        "summary": "Register New User",
        "requestBody": {
          "content": {
            "application/x-www-form-urlencoded": {
              "schema": {
                "type": "object",
                "required": ["name", "email", "password"],
                "properties": {
                  "name": {
                    "type": "string",
                    "description": "full name of the user (accepts spaces)",
                    "example": "New User"
                  },
                  "email": {
                    "type": "string",
                    "description": "email of the user (for notifications and login)",
                    "example": "newuser@example.com"
                  },
                  "password": {
                    "type": "string",
                    "description": "password (to be used for logging in)",
                    "example": "pasword123"
                  }
                }
              }
            }
          }
        },
        "responses": {
          "200": {
            "description": "Successful response",
            "content": {
              "application/json": {}
            }
          }
        }
      }
    }
  }
}
